drf_yasg-stubs/__init__.pyi
drf_yasg-stubs/app_settings.pyi
drf_yasg-stubs/codecs.pyi
drf_yasg-stubs/errors.pyi
drf_yasg-stubs/generators.pyi
drf_yasg-stubs/middleware.pyi
drf_yasg-stubs/openapi.pyi
drf_yasg-stubs/renderers.pyi
drf_yasg-stubs/utils.pyi
drf_yasg-stubs/views.pyi
drf_yasg-stubs/inspectors/__init__.pyi
drf_yasg-stubs/inspectors/base.pyi
drf_yasg-stubs/inspectors/field.pyi
drf_yasg-stubs/inspectors/query.pyi
drf_yasg-stubs/inspectors/view.pyi
drf_yasg-stubs/management/__init__.pyi
drf_yasg-stubs/management/commands/__init__.pyi
drf_yasg-stubs/management/commands/generate_swagger.pyi
drf_yasg_stubs-0.1.4.dist-info/LICENSE.txt
drf_yasg_stubs-0.1.4.dist-info/METADATA
drf_yasg_stubs-0.1.4.dist-info/WHEEL
drf_yasg_stubs-0.1.4.dist-info/top_level.txt
drf_yasg_stubs-0.1.4.dist-info/RECORD
