Metadata-Version: 2.1
Name: drf-yasg-stubs
Version: 0.1.4
Summary: Typing stubs for drf-yasg library (PEP 484 stubs for Mypy and PyCharm)
Home-page: https://github.com/intgr/drf-yasg-stubs
Author: Marti Raudsepp
Author-email: marti@juffo.org
License: MIT
Platform: UNKNOWN
Classifier: Framework :: Django
Classifier: Intended Audience :: Developers
Classifier: Development Status :: 3 - Alpha
Classifier: License :: OSI Approved :: BSD License
Requires-Python: >=3.6
License-File: LICENSE.txt
